apidecorators/__init__.py
apidecorators/api.py
apidecorators/fields.py
apidecorators/hooks.py
apidecorators-0.2.6.dist-info/LICENSE
apidecorators-0.2.6.dist-info/METADATA
apidecorators-0.2.6.dist-info/WHEEL
apidecorators-0.2.6.dist-info/top_level.txt
apidecorators-0.2.6.dist-info/RECORD
