Metadata-Version: 2.1
Name: apidecorators
Version: 0.2.6
Summary: API Decorators
Home-page: https://gitlab.com/miguel.alarcos/apidecorators
Author: Miguel Ángel Alarcos Torrecillas
Author-email: miguel.alarcos@gmail.com
License: UNKNOWN
Platform: UNKNOWN
Classifier: Programming Language :: Python :: 3
Classifier: License :: OSI Approved :: MIT License
Classifier: Operating System :: OS Independent
Requires-Dist: PyJWT (>=1.6.4)
Requires-Dist: aiohttp (>=3.4.4)
Requires-Dist: flatten-dict (>=0.0.3.post1)
Requires-Dist: motor (>=2.0.0)
